degex/__init__.py
degex/_modidx.py
degex/adata.py
degex/plots.py
degex/preprocessing.py
degex/static.py
degex/types.py
degex/utils.py
degex-0.0.24.dist-info/LICENSE
degex-0.0.24.dist-info/METADATA
degex-0.0.24.dist-info/WHEEL
degex-0.0.24.dist-info/entry_points.txt
degex-0.0.24.dist-info/top_level.txt
degex-0.0.24.dist-info/RECORD
