Metadata-Version: 2.1
Name: degex
Version: 0.0.24
Summary: Detect Gene Expression in Single-CEll data
Home-page: https://github.com/dsm-72/degex
Author: dsm-72
Author-email: sumner.magruder@yale.edu
License: Apache Software License 2.0
Keywords: nbdev jupyter notebook python single cell detect gene expression spot marker genes
Classifier: Development Status :: 4 - Beta
Classifier: Intended Audience :: Developers
Classifier: Natural Language :: English
Classifier: Programming Language :: Python :: 3.10
Classifier: License :: OSI Approved :: Apache Software License
Requires-Python: >=3.10
License-File: LICENSE
Requires-Dist: pandas
Requires-Dist: scipy
Requires-Dist: seaborn
Requires-Dist: scikit-learn
Requires-Dist: numpy (>=1.22)
Requires-Dist: graphtools
Requires-Dist: matplotlib
Requires-Dist: scanpy
Requires-Dist: anndata
Requires-Dist: iza
Requires-Dist: phate
Requires-Dist: scprep
Requires-Dist: magic-impute
Requires-Dist: scrublet
Provides-Extra: dev
